sewerpipe/__init__.py
sewerpipe/airflow.py
sewerpipe/changedir.py
sewerpipe/dummy.py
sewerpipe/main.py
sewerpipe/task.py
sewerpipe/utils.py
sewerpipe/vscode.py
sewerpipe/workflows.py
sewerpipe-0.4.3.dist-info/METADATA
sewerpipe-0.4.3.dist-info/WHEEL
sewerpipe-0.4.3.dist-info/entry_points.txt
sewerpipe-0.4.3.dist-info/RECORD
