Metadata-Version: 2.1
Name: sewerpipe
Version: 0.4.3
Summary: Ties your debbuging workflow to automated workflows elsewhere
License: MIT
Author: Chris Czarnecki
Author-email: cczarnec@uwaterloo.ca
Requires-Python: >=3.10,<3.13
Classifier: License :: OSI Approved :: MIT License
Classifier: Programming Language :: Python :: 3
Classifier: Programming Language :: Python :: 3.10
Classifier: Programming Language :: Python :: 3.11
Requires-Dist: apache-airflow (>=2.9.1,<3.0.0)
Requires-Dist: click (>=8.1.7,<9.0.0)
Requires-Dist: confuk (>=0.2.0,<0.3.0)
Requires-Dist: pydantic (>=2.7.3,<3.0.0)
Requires-Dist: rich (>=13.7.1,<14.0.0)
